english_pidgin_dict/__init__.py
english_pidgin_dict/data.json
english_pidgin_dict/english_pidgin_dict.py
english_pidgin_dictionary-0.0.6.dist-info/LICENSE.txt
english_pidgin_dictionary-0.0.6.dist-info/METADATA
english_pidgin_dictionary-0.0.6.dist-info/WHEEL
english_pidgin_dictionary-0.0.6.dist-info/top_level.txt
english_pidgin_dictionary-0.0.6.dist-info/RECORD
