Metadata-Version: 2.1
Name: english-pidgin-dictionary
Version: 0.0.6
Summary: A simple pidgin-english dictionary for various applications
Home-page: https://github.com/Zeecoworld/pidgin-english-dictionary
Author: Isaac Yakubu
Author-email: engrisaac1234@gmail.com
Classifier: License :: OSI Approved :: MIT License
Classifier: Programming Language :: Python :: 3
Classifier: Operating System :: OS Independent
License-File: LICENSE.txt
